tests/__init__.py
tests/test_veritas.py
veritas/__init__.py
veritas-0.1.12.dist-info/LICENSE
veritas-0.1.12.dist-info/METADATA
veritas-0.1.12.dist-info/WHEEL
veritas-0.1.12.dist-info/top_level.txt
veritas-0.1.12.dist-info/RECORD
